gpt2/__init__.py
gpt2/client.py
gpt2-0.0.4.dist-info/LICENSE
gpt2-0.0.4.dist-info/METADATA
gpt2-0.0.4.dist-info/WHEEL
gpt2-0.0.4.dist-info/top_level.txt
gpt2-0.0.4.dist-info/RECORD
