Metadata-Version: 2.1
Name: gpt2
Version: 0.0.4
Summary: API client for GPT-2 text generator cloud hosted by Open Medical IO
Home-page: https://github.com/open-medical-io/cloud-gpt-2
Author: Open Medical IO
Author-email: info@openmedical.io
License: UNKNOWN
Platform: UNKNOWN
Classifier: Programming Language :: Python :: 3
Classifier: License :: OSI Approved :: MIT License
Classifier: Operating System :: OS Independent
